{
    "state": {
        "timestamp": 1734010421736718,
        "zobrist_hash": "6173847443439961829",
        "note": "",
        "name": "S1965M",
        "units": {
            "AUSTRIA": [
                "A GRE",
                "A TYR",
                "A TRI",
                "A ROM"
            ],
            "ENGLAND": [
                "F LON",
                "A WAL",
                "A YOR"
            ],
            "FRANCE": [
                "A BUR",
                "A PIE",
                "F MAR",
                "A POR",
                "A PAR"
            ],
            "GERMANY": [],
            "ITALY": [
                "A TUN"
            ],
            "RUSSIA": [
                "A BOH",
                "A BUL",
                "F RUM",
                "A LVN",
                "F BLA",
                "A WAR",
                "A HOL",
                "A MOS",
                "F PRU",
                "A STP",
                "A MUN",
                "A BEL",
                "A VEN",
                "A VIE",
                "A FIN"
            ],
            "TURKEY": [
                "F ANK",
                "A SIL",
                "A UKR",
                "A SEV"
            ]
        },
        "retreats": {
            "AUSTRIA": {},
            "ENGLAND": {},
            "FRANCE": {},
            "GERMANY": {},
            "ITALY": {},
            "RUSSIA": {},
            "TURKEY": {}
        },
        "centers": {
            "AUSTRIA": [
                "TRI",
                "GRE",
                "NAP",
                "ROM"
            ],
            "ENGLAND": [
                "LVP",
                "LON",
                "EDI"
            ],
            "FRANCE": [
                "BRE",
                "MAR",
                "PAR",
                "POR",
                "SPA"
            ],
            "GERMANY": [],
            "ITALY": [
                "TUN"
            ],
            "RUSSIA": [
                "MOS",
                "STP",
                "SWE",
                "NWY",
                "DEN",
                "HOL",
                "KIE",
                "WAR",
                "RUM",
                "SER",
                "BEL",
                "BUL",
                "BER",
                "BUD",
                "MUN",
                "VIE",
                "VEN"
            ],
            "TURKEY": [
                "ANK",
                "SMY",
                "CON",
                "SEV"
            ]
        },
        "homes": {
            "AUSTRIA": [
                "BUD",
                "TRI",
                "VIE"
            ],
            "ENGLAND": [
                "EDI",
                "LON",
                "LVP"
            ],
            "FRANCE": [
                "BRE",
                "MAR",
                "PAR"
            ],
            "GERMANY": [
                "BER",
                "KIE",
                "MUN"
            ],
            "ITALY": [
                "NAP",
                "ROM",
                "VEN"
            ],
            "RUSSIA": [
                "MOS",
                "SEV",
                "STP",
                "WAR"
            ],
            "TURKEY": [
                "ANK",
                "CON",
                "SMY"
            ]
        },
        "influence": {
            "AUSTRIA": [
                "ION",
                "GRE",
                "ALB",
                "ADR",
                "GAL",
                "APU",
                "NAP",
                "TYR",
                "TRI",
                "ROM"
            ],
            "ENGLAND": [
                "ENG",
                "LON",
                "CLY",
                "EDI",
                "LVP",
                "WAL",
                "YOR"
            ],
            "FRANCE": [
                "TYS",
                "LYO",
                "WES",
                "PIC",
                "MAO",
                "BUR",
                "TUS",
                "SPA",
                "GAS",
                "PIE",
                "MAR",
                "BRE",
                "POR",
                "PAR"
            ],
            "GERMANY": [
                "SKA"
            ],
            "ITALY": [
                "NAF",
                "TUN"
            ],
            "RUSSIA": [
                "MOS",
                "IRI",
                "NAO",
                "NTH",
                "BOT",
                "SER",
                "BOH",
                "NWG",
                "RUH",
                "BAR",
                "BUL",
                "RUM",
                "KIE",
                "BAL",
                "LVN",
                "BLA",
                "DEN",
                "BER",
                "BUD",
                "WAR",
                "HOL",
                "SWE",
                "PRU",
                "STP",
                "NWY",
                "MUN",
                "BEL",
                "VEN",
                "VIE",
                "FIN"
            ],
            "TURKEY": [
                "ANK",
                "CON",
                "SYR",
                "SIL",
                "SMY",
                "ARM",
                "EAS",
                "AEG",
                "UKR",
                "SEV"
            ]
        },
        "civil_disorder": {
            "AUSTRIA": 0,
            "ENGLAND": 0,
            "FRANCE": 0,
            "GERMANY": 0,
            "ITALY": 0,
            "RUSSIA": 0,
            "TURKEY": 0
        },
        "builds": {
            "AUSTRIA": {
                "count": 0,
                "homes": []
            },
            "ENGLAND": {
                "count": 0,
                "homes": []
            },
            "FRANCE": {
                "count": 0,
                "homes": []
            },
            "GERMANY": {
                "count": 0,
                "homes": []
            },
            "ITALY": {
                "count": 0,
                "homes": []
            },
            "RUSSIA": {
                "count": 0,
                "homes": []
            },
            "TURKEY": {
                "count": 0,
                "homes": []
            }
        },
        "game_id": "JoVij8Ui8a6vAK11",
        "map": "standard",
        "rules": [
            "NO_PRESS",
            "POWER_CHOICE"
        ]
    },
    "alterations": {
        "AUSTRIA": [],
        "ENGLAND": [],
        "FRANCE": [],
        "GERMANY": [],
        "ITALY": [],
        "RUSSIA": [
            [
                "A BOH - MUN",
                1.0
            ],
            [
                "A BOH - TYR",
                0.5418099751902491
            ],
            [
                "A BOH H",
                0.3064599475135797
            ],
            [
                "A BOH S A MUN",
                0.26944552595242593
            ],
            [
                "A BOH S A TYR - MUN",
                0.2213455792908148
            ],
            [
                "A BOH S A SIL - MUN",
                0.21602543457927345
            ],
            [
                "A BUL - CON",
                1.0
            ],
            [
                "A BUL H",
                0.5009207927996094
            ],
            [
                "A BUL S A SEV - RUM",
                0.13956527267466776
            ],
            [
                "A BUL - RUM",
                0.10973472346717175
            ],
            [
                "A BUL - SER",
                0.0897861763826756
            ],
            [
                "A BUL S F BLA - CON",
                0.04589893029203789
            ],
            [
                "F RUM - BLA",
                1.0
            ],
            [
                "F RUM - BUL/EC",
                0.7693278311945624
            ],
            [
                "F RUM H",
                0.5663061619583749
            ],
            [
                "F RUM S A BUL",
                0.21357950189831743
            ],
            [
                "F RUM S A MOS - SEV",
                0.16048666465711586
            ],
            [
                "F RUM - SEV",
                0.13772575050805486
            ],
            [
                "A LVN S A MOS",
                1.0
            ],
            [
                "A LVN - PRU",
                0.8121331858377971
            ],
            [
                "A LVN S A WAR",
                0.727000529021718
            ],
            [
                "A LVN - STP",
                0.34126989349010656
            ],
            [
                "A LVN - WAR",
                0.32109128386606195
            ],
            [
                "A LVN H",
                0.3009523164758937
            ],
            [
                "F BLA - CON",
                1.0
            ],
            [
                "F BLA H",
                0.8795598084561245
            ],
            [
                "F BLA S A SEV",
                0.2700654425933265
            ],
            [
                "F BLA - BUL/EC",
                0.23611555134237341
            ],
            [
                "F BLA S A BUL - CON",
                0.2239394719964662
            ],
            [
                "F BLA - RUM",
                0.19213863726273878
            ],
            [
                "A WAR - SIL",
                1.0
            ],
            [
                "A WAR - GAL",
                0.7149936141049046
            ],
            [
                "A WAR - UKR",
                0.40684447398606793
            ],
            [
                "A WAR H",
                0.29297824656906596
            ],
            [
                "A WAR S A MOS",
                0.26052608586980014
            ],
            [
                "A WAR S A SIL",
                0.24080050039177334
            ],
            [
                "A HOL H",
                1.0
            ],
            [
                "A HOL - BEL",
                0.9358722463746053
            ],
            [
                "A HOL - KIE",
                0.7975862301249335
            ],
            [
                "A HOL - RUH",
                0.4376661051660405
            ],
            [
                "A HOL S A RUH - BEL",
                0.310037139837804
            ],
            [
                "A HOL S F BEL",
                0.16620857087643878
            ],
            [
                "A MOS - SEV",
                1.0
            ],
            [
                "A MOS - UKR",
                0.7010270238337956
            ],
            [
                "A MOS S A WAR",
                0.6328926577795649
            ],
            [
                "A MOS H",
                0.36237136442959955
            ],
            [
                "A MOS - WAR",
                0.35833511672155677
            ],
            [
                "A MOS - STP",
                0.30915864607240195
            ],
            [
                "F PRU - BER",
                1.0
            ],
            [
                "F PRU - BAL",
                0.731052613729978
            ],
            [
                "F PRU H",
                0.5676524244624456
            ],
            [
                "F PRU S A BER",
                0.43275693035539325
            ],
            [
                "F PRU - LVN",
                0.31893922771280603
            ],
            [
                "F PRU S A SIL - BER",
                0.07032661400794897
            ],
            [
                "A STP - NWY",
                1.0
            ],
            [
                "A STP - LVN",
                0.4834287711749255
            ],
            [
                "A STP S A MOS",
                0.40369187473021634
            ],
            [
                "A STP H",
                0.33500871097533685
            ],
            [
                "A STP - MOS",
                0.3235148770047307
            ],
            [
                "A STP - FIN",
                0.08232049767409358
            ],
            [
                "A MUN H",
                1.0
            ],
            [
                "A MUN - RUH",
                0.5743353631783816
            ],
            [
                "A MUN S A BUR",
                0.5069985530511539
            ],
            [
                "A MUN - BUR",
                0.3587008461196264
            ],
            [
                "A MUN - TYR",
                0.3367193416657282
            ],
            [
                "A MUN S A BOH - TYR",
                0.30550123985321875
            ],
            [
                "A BEL - PIC",
                1.0
            ],
            [
                "A BEL H",
                0.8435077207587075
            ],
            [
                "A BEL S A BUR",
                0.7537086848225266
            ],
            [
                "A BEL - RUH",
                0.6436877543185262
            ],
            [
                "A BEL - HOL",
                0.4871902866649285
            ],
            [
                "A BEL - BUR",
                0.2495307372617712
            ],
            [
                "A VEN - PIE",
                1.0
            ],
            [
                "A VEN S A TYR",
                0.7180813566211384
            ],
            [
                "A VEN H",
                0.6960619897623456
            ],
            [
                "A VEN S A ROM",
                0.4564845533733925
            ],
            [
                "A VEN S A ROM - TUS",
                0.37390366167826194
            ],
            [
                "A VEN - TUS",
                0.2273403432728901
            ],
            [
                "A VIE S A TYR",
                1.0
            ],
            [
                "A VIE - BOH",
                0.5040690479729596
            ],
            [
                "A VIE - BUD",
                0.22569927883578866
            ],
            [
                "A VIE H",
                0.17237295550358545
            ],
            [
                "A VIE - TYR",
                0.11903632729040121
            ],
            [
                "A VIE - GAL",
                0.05119372155373575
            ],
            [
                "A FIN - SWE",
                1.0
            ],
            [
                "A FIN - NWY",
                0.5735136897424417
            ],
            [
                "A FIN S A STP",
                0.21520081093229196
            ],
            [
                "A FIN - STP",
                0.18375842756120933
            ],
            [
                "A FIN H",
                0.11791697454927207
            ],
            [
                "A FIN S A STP - NWY",
                0.05947742981382743
            ]
        ],
        "TURKEY": []
    }
}